dhcp_leases/__init__.py
dhcp_leases/dhcpleases.py
dhcp_leases/test_DhcpLeases.py
dhcp_leases/test_lease.py
dhcp_leases/test_lease6.py
dhcp_leases-0.1.6.dist-info/LICENSE
dhcp_leases-0.1.6.dist-info/METADATA
dhcp_leases-0.1.6.dist-info/WHEEL
dhcp_leases-0.1.6.dist-info/top_level.txt
dhcp_leases-0.1.6.dist-info/RECORD
