Metadata-Version: 2.1
Name: dhcp-leases
Version: 0.1.6
Summary: Small python module for reading /var/lib/dhcp/dhcpd.leases from isc-dhcp-server
Home-page: https://github.com/acikogun/python-dhcp-leases
Author: Ogun Acik
Author-email: acikogun@gmail.com
License: MIT
Platform: UNKNOWN
Classifier: Development Status :: 5 - Production/Stable
Classifier: Intended Audience :: Developers
Classifier: License :: OSI Approved :: MIT License
Classifier: Operating System :: OS Independent
Classifier: Topic :: Software Development
Classifier: Programming Language :: Python :: 2
Classifier: Programming Language :: Python :: 2.7
Classifier: Programming Language :: Python :: 3
Classifier: Programming Language :: Python :: 3.4
Classifier: Programming Language :: Python :: 3.5
Classifier: Programming Language :: Python :: 3.6
Classifier: Programming Language :: Python :: 3.7
Classifier: Programming Language :: Python :: 3.8
